PyDemoTest/__init__.py
PyDemoTest/__version__.py
PyDemoTest/main.py
PyDemoTest-0.1.2.dist-info/METADATA
PyDemoTest-0.1.2.dist-info/WHEEL
PyDemoTest-0.1.2.dist-info/top_level.txt
PyDemoTest-0.1.2.dist-info/RECORD
